nonebot_hk_reporter/__init__.py
nonebot_hk_reporter/config.py
nonebot_hk_reporter/config_manager.py
nonebot_hk_reporter/platform/__init__.py
nonebot_hk_reporter/platform/arknights.py
nonebot_hk_reporter/platform/bilibili.py
nonebot_hk_reporter/platform/monster_siren.py
nonebot_hk_reporter/platform/ncm_artist.py
nonebot_hk_reporter/platform/platform.py
nonebot_hk_reporter/platform/rss.py
nonebot_hk_reporter/platform/wechat.py
nonebot_hk_reporter/platform/weibo.py
nonebot_hk_reporter/plugin_config.py
nonebot_hk_reporter/post.py
nonebot_hk_reporter/scheduler.py
nonebot_hk_reporter/send.py
nonebot_hk_reporter/types.py
nonebot_hk_reporter/utils.py
nonebot_hk_reporter-0.3.3.dist-info/LICENSE
nonebot_hk_reporter-0.3.3.dist-info/WHEEL
nonebot_hk_reporter-0.3.3.dist-info/METADATA
nonebot_hk_reporter-0.3.3.dist-info/RECORD
