Metadata-Version: 2.1
Name: nonebot-hk-reporter
Version: 0.3.3
Summary: Subscribe message from social medias
Home-page: https://github.com/felinae98/nonebot-hk-reporter
License: MIT
Keywords: nonebot,nonebot2,qqbot
Author: felinae98
Author-email: felinae225@qq.com
Requires-Python: >=3.9,<4.0
Classifier: Development Status :: 2 - Pre-Alpha
Classifier: License :: OSI Approved :: MIT License
Classifier: Operating System :: POSIX :: Linux
Classifier: Programming Language :: Python :: 3
Classifier: Programming Language :: Python :: 3.9
Classifier: Programming Language :: Python :: Implementation :: CPython
Requires-Dist: apscheduler (>=3.7.0,<4.0.0)
Requires-Dist: bs4 (>=0.0.1,<0.0.2)
Requires-Dist: feedparser (>=6.0.2,<7.0.0)
Requires-Dist: httpx (>=0.16.1,<1.0.0)
Requires-Dist: nonebot-adapter-cqhttp (>=2.0.0-alpha.15,<3.0.0)
Requires-Dist: nonebot2 (>=2.0.0-alpha.15,<3.0.0)
Requires-Dist: pillow (>=8.1.0,<9.0.0)
Requires-Dist: pyppeteer (>=0.2.5,<0.3.0)
Requires-Dist: tinydb (>=4.3.0,<5.0.0)
